collei/__init__.py
collei/client.py
collei/manager/__init__.py
collei/manager/nsfw.py
collei/manager/sfw.py
collei/model/__init__.py
collei/model/enums/__init__.py
collei/model/enums/categories/__init__.py
collei/model/enums/categories/nsfw.py
collei/model/enums/categories/sfw.py
collei/model/image.py
collei/py.typed
collei-1.0.2.dist-info/LICENSE
collei-1.0.2.dist-info/METADATA
collei-1.0.2.dist-info/WHEEL
collei-1.0.2.dist-info/RECORD
